LICENSE
MANIFEST.in
README.md
setup.py
bztt_excl/__init__.py
bztt_excl/__version__.py
bztt_excl/bzttExcl.py
bztt_excl.egg-info/PKG-INFO
bztt_excl.egg-info/SOURCES.txt
bztt_excl.egg-info/dependency_links.txt
bztt_excl.egg-info/requires.txt
bztt_excl.egg-info/top_level.txt
test/__init__.py
test/client copy.py
test/client.py